{"file": {"path": "/Users/dakixr/Desktop/github/scc/tmp-data/metadata/KnowledgeCaptureAndDiscoveryANDmintproject/file_uploader/upload_dir.py", "fileNameBase": "upload_dir", "extension": "py"}, "dependencies": [{"import": "owncloud", "type": "external"}, {"import": "os", "type": "external"}, {"import": "csv", "type": "external"}], "functions": {"write_csv": {"args": ["csv_dict", "csv_columns", "csv_file"], "min_max_lineno": {"min_lineno": 16, "max_lineno": 25}, "calls": ["open", "csv.DictWriter", "csv.DictWriter.writeheader", "print", "csv.DictWriter.writerow"], "store_vars_calls": {"writer": "csv.DictWriter"}}, "create_dir_owncloud": {"args": ["dir"], "min_max_lineno": {"min_lineno": 26, "max_lineno": 33}, "calls": ["oc.file_info", "print", "print", "oc.mkdir"], "store_vars_calls": {"details": "oc.file_info"}}}, "body": {"calls": ["owncloud.Client", "owncloud.Client.login", "upload_dir.create_dir_owncloud", "upload_dir.write_csv"], "store_vars_calls": {"oc": "owncloud.Client"}}, "is_test": false}