{"file": {"path": "/Users/dakixr/Desktop/github/scc/tmp-data/metadata/KnowledgeCaptureAndDiscoveryANDmintproject/wings-client/wings/api_client.py", "fileNameBase": "api_client", "extension": "py"}, "dependencies": [{"import": "atexit", "type": "external"}, {"import": "importlib", "type": "external"}, {"import": "logging", "type": "external"}, {"import": "requests", "type": "external"}], "classes": {"ApiClient": {"min_max_lineno": {"min_lineno": 8, "max_lineno": 86}, "methods": {"__init__": {"args": ["self"], "min_max_lineno": {"min_lineno": 9, "max_lineno": 22}, "calls": ["requests.Session", "atexit.register", "api_client.ApiClient.get_export_url", "api_client.ApiClient.get_export_url", "api_client.ApiClient.get_export_url", "api_client.ApiClient.login", "ValueError"], "store_vars_calls": {"self.session": "requests.Session"}}, "get_server": {"args": ["self"], "min_max_lineno": {"min_lineno": 23, "max_lineno": 25}}, "get_username": {"args": ["self"], "min_max_lineno": {"min_lineno": 26, "max_lineno": 28}}, "login": {"args": ["self", "password"], "min_max_lineno": {"min_lineno": 29, "max_lineno": 36}, "calls": ["api_client.ApiClient.session.get", "api_client.ApiClient.session.post"], "store_vars_calls": {"response": "self.session.post"}}, "logout": {"args": ["self"], "min_max_lineno": {"min_lineno": 37, "max_lineno": 40}, "calls": ["api_client.ApiClient.session.get", "api_client.ApiClient.session.close"]}, "session": {"args": ["self"], "min_max_lineno": {"min_lineno": 41, "max_lineno": 43}}, "_initialize": {"args": ["self", "name"], "min_max_lineno": {"min_lineno": 44, "max_lineno": 54}, "calls": ["importlib.import_module", "getattr", "getattr.", "logging.error", "name.title", "logging.error"], "store_vars_calls": {"module_": "importlib.import_module", "class_": "getattr"}}, "close": {"doc": {"short_description": "Shutdown sessions across all instantiated services"}, "args": ["self"], "min_max_lineno": {"min_lineno": 55, "max_lineno": 60}, "calls": ["api_client.ApiClient.logout"]}, "__getattr__": {"args": ["self", "attr"], "min_max_lineno": {"min_lineno": 61, "max_lineno": 68}, "calls": ["setattr", "getattr", "setattr", "getattr", "api_client.ApiClient._initialize"]}, "get_request_url": {"args": ["self"], "min_max_lineno": {"min_lineno": 69, "max_lineno": 71}}, "get_export_url": {"args": ["self"], "min_max_lineno": {"min_lineno": 72, "max_lineno": 75}}, "check_request": {"args": ["resp"], "returns": [["resp"]], "min_max_lineno": {"min_lineno": 77, "max_lineno": 86}, "calls": ["resp.raise_for_status"]}}}}, "is_test": false}