{"file": {"path": "/Users/dakixr/Desktop/github/scc/tmp-data/metadata/KnowledgeCaptureAndDiscoveryANDmintproject/P4ML-UI/dsbox-ta2/python/run.py", "fileNameBase": "run", "extension": "py", "doc": {"short_description": "Command Line Interface for running the DSBox TA2 Planner", "full": "Command Line Interface for running the DSBox TA2 Planner"}}, "dependencies": [{"from_module": "dsbox_dev_setup", "import": "path_setup", "type": "external"}, {"import": "sys", "type": "external"}, {"import": "os", "type": "external"}, {"import": "argparse", "type": "external"}, {"from_module": "dsbox.planner.controller", "import": "Controller", "type": "external"}, {"from_module": "dsbox.planner.controller", "import": "Feature", "type": "external"}, {"from_module": "dsbox.planner.event_handler", "import": "PlannerEventHandler", "type": "external"}], "functions": {"main": {"doc": {"short_description": "Command line options."}, "args": ["argv"], "min_max_lineno": {"min_lineno": 23, "max_lineno": 80}, "calls": ["os.path.basename", "str", "argparse.ArgumentParser", "argparse.ArgumentParser.add_argument", "argparse.ArgumentParser.add_argument", "argparse.ArgumentParser.add_argument", "argparse.ArgumentParser.add_argument", "argparse.ArgumentParser.add_argument", "argparse.ArgumentParser.parse_args", "os.path.basename", "dsbox.planner.controller.Controller", "dsbox.planner.controller.Controller.initialize_simple", "dsbox.planner.controller.Controller.load_problem", "dsbox.planner.controller.Controller.initialize_training_data_from_config", "dsbox.planner.controller.Controller.initialize_planners", "dsbox.planner.controller.Controller.train", "sys.argv.extend", "__import__().__doc__.split", "sys.stderr.write", "sys.stderr.write", "exit", "print", "dsbox.planner.event_handler.PlannerEventHandler", "__import__"], "store_vars_calls": {"program_name": "os.path.basename", "program_build_date": "str", "parser": "argparse.ArgumentParser", "args": "parser.parse_args", "problem_name": "os.path.basename", "controller": "Controller"}}}, "body": {"calls": ["dsbox_dev_setup.path_setup"]}, "main_info": {"main_flag": 1, "type": "script"}, "is_test": false}