{"file": {"path": "/Users/dakixr/Desktop/github/scc/tmp-data/metadata/KnowledgeCaptureAndDiscoveryANDmintproject/mic/src/mic/resources/data_transformation.py", "fileNameBase": "data_transformation", "extension": "py"}, "dependencies": [{"import": "logging", "type": "external"}, {"import": "modelcatalog", "type": "external"}, {"from_module": "mic.model_catalog_utils", "import": "get_api", "type": "external"}, {"from_module": "modelcatalog", "import": "ApiException", "type": "external"}, {"from_module": "modelcatalog", "import": "DataTransformation", "type": "external"}], "classes": {"DataTransformationCli": {"min_max_lineno": {"min_lineno": 10, "max_lineno": 38}, "methods": {"__init__": {"args": ["self", "profile"], "min_max_lineno": {"min_lineno": 13, "max_lineno": 15}}, "get": {"args": ["self"], "returns": [["api_response"]], "min_max_lineno": {"min_lineno": 16, "max_lineno": 25}, "calls": ["mic.model_catalog_utils.get_api", "modelcatalog.DataTransformationApi", "modelcatalog.DataTransformationApi.datatransformations_get"], "store_vars_calls": {"api_instance": "modelcatalog.DataTransformationApi", "api_response": "api_instance.datatransformations_get"}}, "post": {"args": ["self", "request"], "returns": [["api_response"], ["api_response"]], "min_max_lineno": {"min_lineno": 26, "max_lineno": 38}, "calls": ["mic.model_catalog_utils.get_api", "modelcatalog.DataTransformationApi", "isinstance", "modelcatalog.DataTransformation", "modelcatalog.DataTransformationApi.datatransformations_post", "logging.error"], "store_vars_calls": {"api_instance": "modelcatalog.DataTransformationApi", "api_response": "api_instance.datatransformations_post"}}}}}, "is_test": false}